pmagent/__init__.py
pmagent/main.py
pmagent/pm_agent.py
pmagent/pm_script.py
PMAgent-0.2.10.dist-info/LICENSE
PMAgent-0.2.10.dist-info/METADATA
PMAgent-0.2.10.dist-info/WHEEL
PMAgent-0.2.10.dist-info/entry_points.txt
PMAgent-0.2.10.dist-info/top_level.txt
PMAgent-0.2.10.dist-info/RECORD
